rtl/pc.sv
module pc (
    input logic clk,
    input logic reset,
    input logic pc_write,
    input logic [15:0] next_pc,
    output logic [15:0] current_pc
);

always_ff @(posedge clk or posedge reset) begin 

    if (reset) begin 
        current_pc <= 16'h0000;
    end
    else if (pc_write) begin 
        current_pc <= next_pc;
    end

end

endmodule

rtl/pc_tb.sv
`timescale 1ns/1ps

module pc_tb;

    logic clk;
    logic reset;
    logic pc_write;
    logic [15:0] next_pc;

    logic [15:0] current_pc;

    pc uut (
        .clk(clk),
        .reset(reset),
        .pc_write(pc_write),
        .next_pc(next_pc),
        .current_pc(current_pc)
    );

    always begin 
        clk = 0;
        #5;
        clk = 1;
        #5;
    end

    initial begin 
        $dumpfile("pc_sim.vcd");
        $dumpvars(0, pc_tb);
    end

    initial begin 
        $monitor("Time: %0t ns | Reset: %b | PCWrite: %b | Next_PC %h | Current_PC: %h", $time, reset, pc_write, next_pc, current_pc);

        $display("PC Simulation:");

        // Case 1: Initialization with Reset Activated
        reset = 1;
        pc_write = 0;
        next_pc = 16'h1000;
        #12;

        // Case 2: Free Reset
        reset = 0;
        #10;

        // Case 3: Enable PCWrite
        pc_write = 1;
        next_pc = 16'h0001;
        #10;

        // Case 4: Next execution cycle

        next_pc = 16'h0002;
        #10;
        next_pc = 16'h0003;
        #10;

        // Case 5: Unenable PCWrite
        pc_write = 0;
        next_pc = 16'h0AFA;
        #20;

        // Case 6: Reset in the middle of the execution
        reset = 1;
        #10;

        // Case 7: Final free reset
        reset = 0;
        #10;

        $display("Simulation ended");
        $finish;

    end




endmodule

rtl/pc_sim.vcd
$date
	Fri Jul 17 11:43:50 2026
$end
$version
	Icarus Verilog
$end
$timescale
	1ps
$end
$scope module pc_tb $end
$var wire 16 ! current_pc [15:0] $end
$var reg 1 " clk $end
$var reg 16 # next_pc [15:0] $end
$var reg 1 $ pc_write $end
$var reg 1 % reset $end
$scope module uut $end
$var wire 1 " clk $end
$var wire 16 & next_pc [15:0] $end
$var wire 1 $ pc_write $end
$var wire 1 % reset $end
$var reg 16 ' current_pc [15:0] $end
$upscope $end
$upscope $end
$enddefinitions $end
$comment Show the parameter values. $end
$dumpall
$end
#0
$dumpvars
b0 '
b1000000000000 &
1%
0$
b1000000000000 #
0"
b0 !
$end
#5000
1"
#10000
0"
#12000
0%
#15000
1"
#20000
0"
#22000
b1 #
b1 &
1$
#25000
b1 !
b1 '
1"
#30000
0"
#32000
b10 #
b10 &
#35000
b10 !
b10 '
1"
#40000
0"
#42000
b11 #
b11 &
#45000
b11 !
b11 '
1"
#50000
0"
#52000
b101011111010 #
b101011111010 &
0$
#55000
1"
#60000
0"
#65000
1"
#70000
0"
#72000
b0 !
b0 '
1%
#75000
1"
#80000
0"
#82000
0%
