rtl/alu.sv
module alu (
    input logic [15:0] a, 
    input logic [15:0] b,
    input logic [3:0] alu_op,
    output logic [15:0] alu_result,
    output logic zero
);

localparam [3:0] OP_ADD = 4'b0001;
localparam [3:0] OP_SUB = 4'b0010;
localparam [3:0] OP_AND = 4'b0011;
localparam [3:0] OP_OR = 4'b0100;
localparam [3:0] OP_XOR = 4'b0101;
localparam [3:0] OP_SIM = 4'b0110;
localparam [3:0] OP_MOV = 4'b0111;
localparam [3:0] OP_LDI = 4'b1000;
localparam [3:0] OP_LOAD = 4'b1001;
localparam [3:0] OP_STORE = 4'b1010;
localparam [3:0] OP_CMP = 4'b1011;
localparam [3:0] OP_BEQ = 4'b1100;
localparam [3:0] OP_BNE = 4'b1101;
localparam [3:0] OP_JMP = 4'b1110;
localparam [3:0] OP_HALT = 4'b1111;
localparam [3:0] OP_NOP = 4'b0000;

always_comb begin
    alu_result = 16'h0000;

    case (alu_op)
        OP_ADD: begin 
            alu_result = a + b;
    end
        OP_SUB: begin
            alu_result = a - b;
        end

        OP_OR: begin 
            alu_result = a | b;
        end

        OP_AND: begin 
            alu_result = a & b;
        end 

        OP_XOR: begin 
            alu_result = a ^ b;
        end
        
        OP_SIM: begin 
                alu_result = 16'd0;
                for (int i = 0; i < 16; i++) begin
                if (a[i] == b[i]) begin
                    alu_result = alu_result + 1;
                 end
                end
        end

        OP_MOV: begin 
            alu_result = a;
        end

        OP_LDI: begin 
            alu_result = b;
        end
        
        OP_LOAD: begin 
            alu_result = a;
        end

        OP_STORE: begin 
            alu_result = a;
        end

        OP_CMP: begin 
            alu_result = a - b;
        end

        OP_BEQ: begin 
            alu_result = a - b;
        end

        OP_BNE: begin 
            alu_result = a - b;
        end

        OP_JMP: begin 
            alu_result = a;
        end

        OP_NOP: begin 
            alu_result = 16'h0000;
        end

        OP_HALT: begin 
            alu_result = 16'h0000;
        end

    default: begin
        alu_result = 16'h0000;
    end
    endcase
end
assign zero = (alu_result == 16'h0000);
endmodule

tb/alu_tb.sv
//ALU Testbench

`timescale 1ns/1ps

module alu_tb;

logic [15:0] a;
logic [15:0] b;
logic [3:0] alu_op;

logic [15:0] alu_result;
logic zero;


alu uut (
    .a(a),
    .b(b),
    .alu_op(alu_op),
    .alu_result(alu_result),
    .zero(zero)
);

// Bloque para generar el archivo de ondas
    initial begin
        $dumpfile("alu_sim.vcd"); // Define el nombre del archivo de salida
        $dumpvars(0, alu_tb);     // Guarda todas las variables desde el nivel alu_tb hacia abajo
    end

    initial begin 
        $monitor("Time: %0t ns | OP: %b | A: %h | B: %h | Result: %h | Zero: %b", $time, alu_op, a, b, alu_result, zero);



    // Initialization test #1
    a = 16'h0000;
    b = 16'h0000;
    alu_op = 4'b0000;
    #10; // <- 10 units of time.


    // NOP Case
    a = 16'h1234;
    b = 16'h5678;
    alu_op = 4'b0000;
    #10;



    // Test: ADD
    a = 16'd15;
    b = 16'd10;
    alu_op = 4'b0001;
    #10;

    // SUB Case
    a = 16'd500;
    b = 16'd120;
    alu_op = 4'b0010;
    #10;

    // AND Case
    a = 16'h0F0F;
    b = 16'hFFFF;
    alu_op = 4'b0011;
    #10;

    // OR Case
    a = 16'hF0F0;
    b = 16'h0F0F;
    alu_op = 4'b0100;
    #10;

    // MOV Case
    a = 16'h55AA;
    b = 16'hFFF;
    alu_op = 4'b0111;
    #10;

    // LOAD case

    a = 16'h00A0;
    b = 16'h0004;
    alu_op = 4'b1001;
    #10;

    // STORE Case

    a = 16'h00B0;
    b = 16'h0008;
    alu_op = 4'b1010;
    #10;

    // BEQ Case
    a = 16'd25;
    b = 16'd25;
    alu_op = 4'b1100;
    #10;

    // BNE Case

    a = 16'd25;
    b = 16'd10;
    alu_op = 4'b1101;
    #10;

    // JMP Case
    a = 16'h03FF;
    b = 16'h0000;
    alu_op = 4'b1110;
    #10;

    // HALT Case
    a = 16'h1234;
    b = 16'h5678;
    alu_op = 4'b1111;
    #10;

    // CMP Case
    a = 16'hA5A5;
    b = 16'hA5A5;
    alu_op = 4'b1011;
    #10;

    // XOR Case
    a = 16'b1111_0000_1100_1010;
    b = 16'b1010_1010_1010_1010;
    alu_op = 4'b0101;
    #10;

    // OPSIM Case
      
        a = 16'b1111_1111_0000_1111; 
        b = 16'b1111_0000_0000_1111; 
        alu_op = 4'b0110; 
        #10;

    // LDI Case

    a = 16'hFFFF;
    b = 16'hABCD;
    alu_op = 4'b1000;
    #10;

    $display("Finished");
    $finish;
end


endmodule

rtl/vcd/alu_sim.vcd
$date
	Fri Jul 17 09:14:49 2026
$end
$version
	Icarus Verilog
$end
$timescale
	1ps
$end
$scope module alu_tb $end
$var wire 1 ! zero $end
$var wire 16 " alu_result [15:0] $end
$var reg 16 # a [15:0] $end
$var reg 4 $ alu_op [3:0] $end
$var reg 16 % b [15:0] $end
$scope module uut $end
$var wire 16 & a [15:0] $end
$var wire 4 ' alu_op [3:0] $end
$var wire 16 ( b [15:0] $end
$var wire 1 ! zero $end
$var parameter 4 ) OP_ADD $end
$var parameter 4 * OP_AND $end
$var parameter 4 + OP_BEQ $end
$var parameter 4 , OP_BNE $end
$var parameter 4 - OP_CMP $end
$var parameter 4 . OP_HALT $end
$var parameter 4 / OP_JMP $end
$var parameter 4 0 OP_LDI $end
$var parameter 4 1 OP_LOAD $end
$var parameter 4 2 OP_MOV $end
$var parameter 4 3 OP_NOP $end
$var parameter 4 4 OP_OR $end
$var parameter 4 5 OP_SIM $end
$var parameter 4 6 OP_STORE $end
$var parameter 4 7 OP_SUB $end
$var parameter 4 8 OP_XOR $end
$var reg 16 9 alu_result [15:0] $end
$scope begin $ivl_for_loop0 $end
$var integer 32 : i [31:0] $end
$upscope $end
$upscope $end
$upscope $end
$enddefinitions $end
$comment Show the parameter values. $end
$dumpall
b101 8
b10 7
b1010 6
b110 5
b100 4
b0 3
b111 2
b1001 1
b1000 0
b1110 /
b1111 .
b1011 -
b1101 ,
b1100 +
b11 *
b1 )
$end
#0
$dumpvars
b0 :
b0 9
b0 (
b0 '
b0 &
b0 %
b0 $
b0 #
b0 "
1!
$end
#10000
b101011001111000 %
b101011001111000 (
b1001000110100 #
b1001000110100 &
#20000
0!
b11001 "
b11001 9
b1 $
b1 '
b1010 %
b1010 (
b1111 #
b1111 &
#30000
0!
b101111100 "
b101111100 9
b10 $
b10 '
b1111000 %
b1111000 (
b111110100 #
b111110100 &
#40000
0!
b111100001111 "
b111100001111 9
b11 $
b11 '
b1111111111111111 %
b1111111111111111 (
b111100001111 #
b111100001111 &
#50000
0!
b1111111111111111 "
b1111111111111111 9
b100 $
b100 '
b111100001111 %
b111100001111 (
b1111000011110000 #
b1111000011110000 &
#60000
0!
b101010110101010 "
b101010110101010 9
b111 $
b111 '
b111111111111 %
b111111111111 (
b101010110101010 #
b101010110101010 &
#70000
0!
b10100000 "
b10100000 9
b1001 $
b1001 '
b100 %
b100 (
b10100000 #
b10100000 &
#80000
0!
b10110000 "
b10110000 9
b1010 $
b1010 '
b1000 %
b1000 (
b10110000 #
b10110000 &
#90000
1!
b0 "
b0 9
b1100 $
b1100 '
b11001 %
b11001 (
b11001 #
b11001 &
#100000
0!
b1111 "
b1111 9
b1101 $
b1101 '
b1010 %
b1010 (
#110000
0!
b1111111111 "
b1111111111 9
b1110 $
b1110 '
b0 %
b0 (
b1111111111 #
b1111111111 &
#120000
1!
b0 "
b0 9
b1111 $
b1111 '
b101011001111000 %
b101011001111000 (
b1001000110100 #
b1001000110100 &
#130000
b1011 $
b1011 '
b1010010110100101 %
b1010010110100101 (
b1010010110100101 #
b1010010110100101 &
#140000
0!
b101101001100000 "
b101101001100000 9
b101 $
b101 '
b1010101010101010 %
b1010101010101010 (
b1111000011001010 #
b1111000011001010 &
#150000
b10000 :
0!
b1100 "
b1100 9
b110 $
b110 '
b1111000000001111 %
b1111000000001111 (
b1111111100001111 #
b1111111100001111 &
#160000
0!
b1010101111001101 "
b1010101111001101 9
b1000 $
b1000 '
b1010101111001101 %
b1010101111001101 (
b1111111111111111 #
b1111111111111111 &
